img2hbterm/__init__.py
img2hbterm/cli.py
img2hbterm-1.0.1.dist-info/licenses/LICENSE
img2hbterm-1.0.1.dist-info/METADATA
img2hbterm-1.0.1.dist-info/WHEEL
img2hbterm-1.0.1.dist-info/entry_points.txt
img2hbterm-1.0.1.dist-info/top_level.txt
img2hbterm-1.0.1.dist-info/RECORD
