Metadata-Version: 2.4
Name: img2hbterm
Version: 1.0.1
Summary: Image to Half-block ANSI art with 256-color XTerm codes.
Author-email: Swee <meow@swee.codes>
License: Apache-2.0
Project-URL: Homepage, https://swee.codes/apps/img2text
Project-URL: Repository, https://git.swee.codes/swee/img2hbterm
Project-URL: Issues, https://git.swee.codes/swee/img2hbterm/issues
Project-URL: Changelog, https://git.swee.codes/swee/img2hbterm/releases
Classifier: Programming Language :: Python :: 3
Classifier: Operating System :: OS Independent
Requires-Python: >=3.9
License-File: LICENSE
Requires-Dist: typer
Requires-Dist: typing-extensions
Requires-Dist: pillow
Requires-Dist: x256
Dynamic: license-file
